code_conductor_bench/__init__.py
code_conductor_bench/localization_agent/tools.py
code_conductor_bench/util/__init__.py
code_conductor_bench/util/tracking.py
code_conductor_bench-0.1.6.dist-info/WHEEL
code_conductor_bench-0.1.6.dist-info/entry_points.txt
code_conductor_bench-0.1.6.dist-info/METADATA
code_conductor_bench-0.1.6.dist-info/RECORD
