Metadata-Version: 2.3
Name: code-conductor-bench
Version: 0.1.6
Summary: A benchmark based on swe-bench that evaluates the conceptual reasoning capabilities of LLMs in the context of software engineering tasks.
Author: ZhuangYumin
Author-email: ZhuangYumin <zymx@pm.me>
Requires-Dist: datasets>=4.0.0
Requires-Dist: jinja2>=3.1.6
Requires-Dist: loguru>=0.7.3
Requires-Dist: mini-swe-agent
Requires-Dist: openai>=1.102.0
Requires-Dist: openai-agents>=0.2.10
Requires-Dist: swebench
Requires-Dist: tenacity>=9.1.2
Requires-Dist: tqdm>=4.67.1
Requires-Dist: wandb>=0.21.3
Requires-Python: >=3.12.11
